sikei/__init__.py
sikei/mediator.py
sikei/py.typed
sikei/response.py
sikei/brokers/__init__.py
sikei/brokers/azure.py
sikei/brokers/protocol.py
sikei/brokers/rabbitmq.py
sikei/brokers/redis.py
sikei/container/__init__.py
sikei/container/di.py
sikei/container/injector.py
sikei/container/protocol.py
sikei/container/rodi.py
sikei/dispatcher/__init__.py
sikei/dispatcher/default.py
sikei/dispatcher/protocol.py
sikei/dispatcher/result.py
sikei/events/__init__.py
sikei/events/emitter.py
sikei/events/event.py
sikei/events/handler.py
sikei/events/map.py
sikei/middlewares/__init__.py
sikei/middlewares/base.py
sikei/middlewares/logging.py
sikei/requests/__init__.py
sikei/requests/handler.py
sikei/requests/map.py
sikei/requests/request.py
sikei-0.2.2.dist-info/METADATA
sikei-0.2.2.dist-info/WHEEL
sikei-0.2.2.dist-info/licenses/LICENSE
sikei-0.2.2.dist-info/RECORD
