Metadata-Version: 2.4
Name: sikei
Version: 0.2.2
Summary: This is a fork from Diator, a Python library for implementing CQRS pattern in your applications. The original project is apparently abandoned.
Project-URL: Homepage, https://github.com/LabMarket/sikei.git
Project-URL: Bug Tracker, https://github.com/LabMarket/sikei/issues
Author-email: Murad Akhundov <akhundov1murad@gmail.com>, José Marcos Gomes <jose.marcos.gomes@gmail.com>
License-Expression: MIT
License-File: LICENSE
Keywords: CQRS,async,asyncio,command,commands,di,diator,event,events,mediator,mediatr,queries,query,sikei
Classifier: Development Status :: 3 - Alpha
Classifier: License :: OSI Approved :: MIT License
Classifier: Operating System :: OS Independent
Classifier: Programming Language :: Python :: 3.10
Classifier: Programming Language :: Python :: 3.11
Requires-Python: >=3.10
Requires-Dist: orjson
Requires-Dist: pydantic>=2.11.1
Provides-Extra: azure
Requires-Dist: azure-servicebus; extra == 'azure'
Provides-Extra: rabbitmq
Requires-Dist: aio-pika; extra == 'rabbitmq'
Provides-Extra: redis
Requires-Dist: redis; extra == 'redis'
Provides-Extra: test
Requires-Dist: aio-pika; extra == 'test'
Requires-Dist: asyncio; extra == 'test'
Requires-Dist: azure-servicebus; extra == 'test'
Requires-Dist: black; extra == 'test'
Requires-Dist: dependency-injector; extra == 'test'
Requires-Dist: di[anyio]; extra == 'test'
Requires-Dist: flake8; extra == 'test'
Requires-Dist: isort; extra == 'test'
Requires-Dist: mkdocs; extra == 'test'
Requires-Dist: mkdocs-material; extra == 'test'
Requires-Dist: mkdocstrings; extra == 'test'
Requires-Dist: mypy; extra == 'test'
Requires-Dist: pytest; extra == 'test'
Requires-Dist: pytest-asyncio; extra == 'test'
Requires-Dist: redis; extra == 'test'
Requires-Dist: rodi; extra == 'test'
Requires-Dist: types-redis; extra == 'test'
Requires-Dist: vulture; extra == 'test'
